telegram_envelope/__init__.py
telegram_envelope/py.typed
telegram_envelope/simple_text_bot.py
telegram_envelope/utils.py
tests/__init__.py
tests/py.typed
tests/telegram_envelope/__init__.py
tests/telegram_envelope/test_simple_text_bot.py
tests/telegram_envelope/test_utils.py
telegram_envelope-0.1.3.dist-info/LICENSE
telegram_envelope-0.1.3.dist-info/METADATA
telegram_envelope-0.1.3.dist-info/WHEEL
telegram_envelope-0.1.3.dist-info/top_level.txt
telegram_envelope-0.1.3.dist-info/RECORD
