Metadata-Version: 2.1
Name: telegram-envelope
Version: 0.1.3
Summary: Micro-helper for AWS Telegram Bots written in Python
Home-page: https://github.com/DaniSancas/telegram-envelope
Author: Dani Sancas
Author-email: lord.sancas@gmail.com
License: UNKNOWN
Platform: UNKNOWN
Classifier: Programming Language :: Python :: 3
Classifier: License :: OSI Approved :: MIT License
Classifier: Operating System :: OS Independent
Requires-Python: >=3.6
